monitoring/__init__.py
monitoring/client.py
llm_monitoring_sascha-0.0.9.dist-info/LICENSE
llm_monitoring_sascha-0.0.9.dist-info/METADATA
llm_monitoring_sascha-0.0.9.dist-info/WHEEL
llm_monitoring_sascha-0.0.9.dist-info/top_level.txt
llm_monitoring_sascha-0.0.9.dist-info/RECORD
