Metadata-Version: 2.1
Name: llm_monitoring_sascha
Version: 0.0.9
Summary: A small example package
Author-email: Sascha Heyer <mail@saschaheyer.de>, Sascha Heyer <sascha@doit.com>
Project-URL: Homepage, https://github.com/pypa/sampleproject
Project-URL: Issues, https://github.com/pypa/sampleproject/issues
Classifier: Programming Language :: Python :: 3
Classifier: License :: OSI Approved :: MIT License
Classifier: Operating System :: OS Independent
License-File: LICENSE
Requires-Dist: google-cloud-pubsub
